[
  {
    "text": "Aguanta el burro",
    "meaning": "Expresión que quiere decir: Espera un momento.",
    "examples": [
      "‘Hey, aguanta el burro que me dejas atrás’"
    ]
  },
  {
    "text": "Aguacatao",
    "meaning": "Persona aburrida, triste o decepcionada.",
    "examples": [
      "‘Ese pelao está como aguacatao’",
      "‘Ey, no estés tanto tiempo aguacatao’"
    ]
  },
  {
    "text": "¡A vaina!",
    "meaning": "Expresión utilizada para demostrar admiración.",
    "examples": [
      "‘¡A vaina!, por fin terminaste la carrera’"
    ]
  },
  {
    "text": "Billullo",
    "meaning": "Dinero en billetes.",
    "examples": [
      "‘Ando con billullo’",
      "‘Me quedé sin billullo’"
    ]
  },
  {
    "text": "Bololó",
    "meaning": "Palabra utilizada cuando las cosas se salen de control. Caos, descontrol, desorden.",
    "examples": [
      "‘¿Viste el cipote bololó que se formó en la fiesta de anoche?’",
      "‘Vámonos de aquí antes de que se forme un bololó’"
    ]
  },
  {
    "text": "Calilla",
    "meaning": "Persona intensa o molesta.",
    "examples": [
      "‘Ese man si es calilla’",
      "‘Oye deja la intensidad, no seas calilla’"
    ]
  },
  {
    "text": "Carretilla",
    "meaning": "Algo falso o que es mentira.",
    "examples": [
      "‘Lo que dijo el presidente es carretilla’",
      "‘No le creas a el, es muy carretillero’"
    ]
  },
  {
    "text": "Emputao",
    "meaning": "Persona brava o enfadada.",
    "examples": [
      "‘Dejalo quieto que está emputao’",
      "‘Deja de joder o me voy a emputar’"
    ]
  },
  {
    "text": "Esa es la que te cae",
    "meaning": "Frase usada cuando una persona sale siempre con lo mismo.",
    "examples": [
      "‘Esa es la que te cae a ti, siempre con la misma vaina’"
    ]
  },
  {
    "text": "Guachafita",
    "meaning": "Situación que predomina el desorden.",
    "examples": [
      "‘Hey, dejen la guachafita y hagamos las cosas en serio’",
      "‘José, me haces el favor y dejas la guachafita’"
    ]
  },
  {
    "text": "Huepaje",
    "meaning": "Grito para mostrar alegría.",
    "examples": [
      "‘¡Huepaje!, bailalo morena’"
    ]
  },
  {
    "text": "Lambón",
    "meaning": "Persona que acusa, delata o adula a alguien.",
    "examples": [
      "‘Ahí viene de la oficina del profesor el lambón ese’",
      "‘Ese pelao es muy lambón’"
    ]
  },
  {
    "text": "Monocuco",
    "meaning": "Palabra utilizada para referirse a algo que está bien o es bonito. Figura del carnaval de barranquilla.",
    "examples": [
      "‘Con esta pinta nueva quedé monocuco’",
      "‘Mira, ahí viene bailando el monocuco’"
    ]
  },
  {
    "text": "Pasarse de piña",
    "meaning": "Expresión que significa: Abusar de la confianza de una persona o sacar provecho de alguien.",
    "examples": [
      "‘Yo te ayudo con el trabajo, pero no te pases de piña’"
    ]
  },
  {
    "text": "Rayúo",
    "meaning": "hace referencia a una persona sobre motivada",
    "examples": [
      "‘Anda rayúo con el regalo que le dieron’",
      "‘Ese rayúo no se quita la camiseta nueva ni para dormir’"
    ]
  }
]